mydream/__init__.py
mydream-0.3.1.dist-info/LICENSE
mydream-0.3.1.dist-info/METADATA
mydream-0.3.1.dist-info/WHEEL
mydream-0.3.1.dist-info/top_level.txt
mydream-0.3.1.dist-info/RECORD
