Metadata-Version: 2.1
Name: mydream
Version: 0.3.1
Summary: A man made Easter-Egg
Home-page: https://github.com/kingjacM
Author: Jack Ma
Author-email: 924756831@qq.com
License: UNKNOWN
Platform: UNKNOWN
Classifier: Programming Language :: Python :: 3
Classifier: License :: OSI Approved :: MIT License
Classifier: Operating System :: OS Independent
